<annotationInfo>
<annotationInfo>
<item  id="11" filename="imageprosseing/imgpro.c" linenumber="86" name="i" contextFuncName="blurf" moduleName="blurf" rtlName="i_fu_646_p2" latency="0" BRAM="-1" DSP="-1" FF="0" LUT="15" fileDirectory="C:\Users\raoja\Desktop\uni\520"><\/item>
<item  id="12" filename="imageprosseing/imgpro.c" linenumber="91" name="icmp_ln91" contextFuncName="blurf" moduleName="blurf" rtlName="icmp_ln91_fu_652_p2" latency="0" BRAM="-1" DSP="-1" FF="0" LUT="11" fileDirectory="C:\Users\raoja\Desktop\uni\520"><\/item>
<item  id="13" filename="imageprosseing/imgpro.c" linenumber="103" name="icmp_ln103" contextFuncName="blurf" moduleName="blurf" rtlName="icmp_ln103_fu_658_p2" latency="0" BRAM="-1" DSP="-1" FF="0" LUT="11" fileDirectory="C:\Users\raoja\Desktop\uni\520"><\/item>
<item  id="14" filename="imageprosseing/imgpro.c" linenumber="75" name="icmp_ln75" contextFuncName="blurf" moduleName="blurf" rtlName="icmp_ln75_fu_664_p2" latency="0" BRAM="-1" DSP="-1" FF="0" LUT="13" fileDirectory="C:\Users\raoja\Desktop\uni\520"><\/item>
<item  id="15" filename="imageprosseing/imgpro.c" linenumber="75" name="add_ln75_1" contextFuncName="blurf" moduleName="blurf" rtlName="add_ln75_1_fu_670_p2" latency="0" BRAM="-1" DSP="-1" FF="0" LUT="19" fileDirectory="C:\Users\raoja\Desktop\uni\520"><\/item>
<item  id="20" filename="imageprosseing/imgpro.c" linenumber="77" name="icmp_ln77" contextFuncName="blurf" moduleName="blurf" rtlName="icmp_ln77_fu_676_p2" latency="0" BRAM="-1" DSP="-1" FF="0" LUT="11" fileDirectory="C:\Users\raoja\Desktop\uni\520"><\/item>
<item  id="21" filename="imageprosseing/imgpro.c" linenumber="75" name="select_ln75" contextFuncName="blurf" moduleName="blurf" rtlName="select_ln75_fu_682_p3" latency="0" BRAM="-1" DSP="-1" FF="0" LUT="7" fileDirectory="C:\Users\raoja\Desktop\uni\520"><\/item>
<item  id="22" filename="imageprosseing/imgpro.c" linenumber="86" name="add_ln86" contextFuncName="blurf" moduleName="blurf" rtlName="add_ln86_fu_690_p2" latency="0" BRAM="-1" DSP="-1" FF="0" LUT="15" fileDirectory="C:\Users\raoja\Desktop\uni\520"><\/item>
<item  id="23" filename="imageprosseing/imgpro.c" linenumber="75" name="select_ln75_1" contextFuncName="blurf" moduleName="blurf" rtlName="select_ln75_1_fu_696_p3" latency="0" BRAM="-1" DSP="-1" FF="0" LUT="7" fileDirectory="C:\Users\raoja\Desktop\uni\520"><\/item>
<item  id="24" filename="imageprosseing/imgpro.c" linenumber="75" name="zext_ln75_1" contextFuncName="blurf" moduleName="blurf" rtlName="mul_ln86_fu_708_p10" latency="0" BRAM="-1" DSP="-1" FF="-1" LUT="-1" fileDirectory="C:\Users\raoja\Desktop\uni\520"><\/item>
<item  id="25" filename="imageprosseing/imgpro.c" linenumber="86" name="mul_ln86" contextFuncName="blurf" moduleName="blurf" rtlName="mul_ln86_fu_708_p2" latency="0" BRAM="-1" DSP="0" FF="0" LUT="33" fileDirectory="C:\Users\raoja\Desktop\uni\520"><\/item>
<item  id="26" filename="imageprosseing/imgpro.c" linenumber="86" name="trunc_ln86" contextFuncName="blurf" moduleName="blurf" rtlName="trunc_ln86_fu_714_p1" latency="0" BRAM="-1" DSP="-1" FF="-1" LUT="-1" fileDirectory="C:\Users\raoja\Desktop\uni\520"><\/item>
<item  id="27" filename="imageprosseing/imgpro.c" linenumber="86" name="zext_ln86" contextFuncName="blurf" moduleName="blurf" rtlName="zext_ln86_fu_820_p1" latency="0" BRAM="-1" DSP="-1" FF="-1" LUT="-1" fileDirectory="C:\Users\raoja\Desktop\uni\520"><\/item>
<item  id="28" filename="imageprosseing/imgpro.c" linenumber="106" name="add_ln106" contextFuncName="blurf" moduleName="blurf" rtlName="add_ln106_fu_824_p2" latency="0" BRAM="-1" DSP="-1" FF="0" LUT="19" fileDirectory="C:\Users\raoja\Desktop\uni\520"><\/item>
<item  id="29" filename="imageprosseing/imgpro.c" linenumber="106" name="zext_ln106" contextFuncName="blurf" moduleName="blurf" rtlName="zext_ln106_fu_829_p1" latency="0" BRAM="-1" DSP="-1" FF="-1" LUT="-1" fileDirectory="C:\Users\raoja\Desktop\uni\520"><\/item>
<item  id="31" filename="imageprosseing/imgpro.c" linenumber="110" name="add_ln110" contextFuncName="blurf" moduleName="blurf" rtlName="add_ln110_fu_834_p2" latency="0" BRAM="-1" DSP="-1" FF="0" LUT="19" fileDirectory="C:\Users\raoja\Desktop\uni\520"><\/item>
<item  id="32" filename="imageprosseing/imgpro.c" linenumber="110" name="zext_ln110" contextFuncName="blurf" moduleName="blurf" rtlName="zext_ln110_fu_839_p1" latency="0" BRAM="-1" DSP="-1" FF="-1" LUT="-1" fileDirectory="C:\Users\raoja\Desktop\uni\520"><\/item>
<item  id="35" filename="imageprosseing/imgpro.c" linenumber="148" name="or_ln148" contextFuncName="blurf" moduleName="blurf" rtlName="or_ln148_fu_1003_p2" latency="0" BRAM="-1" DSP="-1" FF="0" LUT="14" fileDirectory="C:\Users\raoja\Desktop\uni\520"><\/item>
<item  id="36" filename="imageprosseing/imgpro.c" linenumber="148" name="zext_ln148" contextFuncName="blurf" moduleName="blurf" rtlName="zext_ln148_fu_1008_p1" latency="0" BRAM="-1" DSP="-1" FF="-1" LUT="-1" fileDirectory="C:\Users\raoja\Desktop\uni\520"><\/item>
<item  id="38" filename="imageprosseing/imgpro.c" linenumber="75" name="select_ln75_2" contextFuncName="blurf" moduleName="blurf" rtlName="select_ln75_2_fu_718_p3" latency="0" BRAM="-1" DSP="-1" FF="0" LUT="7" fileDirectory="C:\Users\raoja\Desktop\uni\520"><\/item>
<item  id="39" filename="imageprosseing/imgpro.c" linenumber="75" name="zext_ln75_2" contextFuncName="blurf" moduleName="blurf" rtlName="mul_ln88_fu_730_p10" latency="0" BRAM="-1" DSP="-1" FF="-1" LUT="-1" fileDirectory="C:\Users\raoja\Desktop\uni\520"><\/item>
<item  id="40" filename="imageprosseing/imgpro.c" linenumber="88" name="mul_ln88" contextFuncName="blurf" moduleName="blurf" rtlName="mul_ln88_fu_730_p2" latency="0" BRAM="-1" DSP="0" FF="0" LUT="33" fileDirectory="C:\Users\raoja\Desktop\uni\520"><\/item>
<item  id="41" filename="imageprosseing/imgpro.c" linenumber="88" name="trunc_ln88" contextFuncName="blurf" moduleName="blurf" rtlName="trunc_ln88_fu_736_p1" latency="0" BRAM="-1" DSP="-1" FF="-1" LUT="-1" fileDirectory="C:\Users\raoja\Desktop\uni\520"><\/item>
<item  id="42" filename="imageprosseing/imgpro.c" linenumber="88" name="zext_ln88" contextFuncName="blurf" moduleName="blurf" rtlName="zext_ln88_fu_1013_p1" latency="0" BRAM="-1" DSP="-1" FF="-1" LUT="-1" fileDirectory="C:\Users\raoja\Desktop\uni\520"><\/item>
<item  id="43" filename="imageprosseing/imgpro.c" linenumber="93" name="add_ln93" contextFuncName="blurf" moduleName="blurf" rtlName="add_ln93_fu_844_p2" latency="0" BRAM="-1" DSP="-1" FF="0" LUT="19" fileDirectory="C:\Users\raoja\Desktop\uni\520"><\/item>
<item  id="44" filename="imageprosseing/imgpro.c" linenumber="93" name="zext_ln93" contextFuncName="blurf" moduleName="blurf" rtlName="zext_ln93_fu_849_p1" latency="0" BRAM="-1" DSP="-1" FF="-1" LUT="-1" fileDirectory="C:\Users\raoja\Desktop\uni\520"><\/item>
<item  id="46" filename="imageprosseing/imgpro.c" linenumber="101" name="add_ln101_3" contextFuncName="blurf" moduleName="blurf" rtlName="add_ln101_3_fu_854_p2" latency="0" BRAM="-1" DSP="-1" FF="0" LUT="19" fileDirectory="C:\Users\raoja\Desktop\uni\520"><\/item>
<item  id="47" filename="imageprosseing/imgpro.c" linenumber="101" name="zext_ln101_2" contextFuncName="blurf" moduleName="blurf" rtlName="zext_ln101_2_fu_859_p1" latency="0" BRAM="-1" DSP="-1" FF="-1" LUT="-1" fileDirectory="C:\Users\raoja\Desktop\uni\520"><\/item>
<item  id="49" filename="imageprosseing/imgpro.c" linenumber="125" name="or_ln125" contextFuncName="blurf" moduleName="blurf" rtlName="or_ln125_fu_1018_p2" latency="0" BRAM="-1" DSP="-1" FF="0" LUT="14" fileDirectory="C:\Users\raoja\Desktop\uni\520"><\/item>
<item  id="50" filename="imageprosseing/imgpro.c" linenumber="125" name="zext_ln125" contextFuncName="blurf" moduleName="blurf" rtlName="zext_ln125_fu_1023_p1" latency="0" BRAM="-1" DSP="-1" FF="-1" LUT="-1" fileDirectory="C:\Users\raoja\Desktop\uni\520"><\/item>
<item  id="55" filename="imageprosseing/imgpro.c" linenumber="91" name="icmp_ln91_2" contextFuncName="blurf" moduleName="blurf" rtlName="icmp_ln91_2_fu_740_p2" latency="0" BRAM="-1" DSP="-1" FF="0" LUT="11" fileDirectory="C:\Users\raoja\Desktop\uni\520"><\/item>
<item  id="56" filename="imageprosseing/imgpro.c" linenumber="75" name="select_ln75_3" contextFuncName="blurf" moduleName="blurf" rtlName="select_ln75_3_fu_746_p3" latency="0" BRAM="-1" DSP="-1" FF="0" LUT="2" fileDirectory="C:\Users\raoja\Desktop\uni\520"><\/item>
<item  id="57" filename="imageprosseing/imgpro.c" linenumber="75" name="zext_ln75" contextFuncName="blurf" moduleName="blurf" rtlName="zext_ln75_fu_754_p1" latency="0" BRAM="-1" DSP="-1" FF="-1" LUT="-1" fileDirectory="C:\Users\raoja\Desktop\uni\520"><\/item>
<item  id="58" filename="imageprosseing/imgpro.c" linenumber="75" name="add_ln75" contextFuncName="blurf" moduleName="blurf" rtlName="add_ln75_fu_758_p2" latency="0" BRAM="-1" DSP="-1" FF="0" LUT="15" fileDirectory="C:\Users\raoja\Desktop\uni\520"><\/item>
<item  id="60" filename="imageprosseing/imgpro.c" linenumber="95" name="mul_ln95" contextFuncName="blurf" moduleName="blurf" rtlName="mul_ln95_fu_868_p2" latency="0" BRAM="-1" DSP="0" FF="0" LUT="41" fileDirectory="C:\Users\raoja\Desktop\uni\520"><\/item>
<item  id="61" filename="imageprosseing/imgpro.c" linenumber="95" name="sext_ln95_1" contextFuncName="blurf" moduleName="blurf" rtlName="sext_ln95_1_fu_874_p1" latency="0" BRAM="-1" DSP="-1" FF="-1" LUT="-1" fileDirectory="C:\Users\raoja\Desktop\uni\520"><\/item>
<item  id="62" filename="imageprosseing/imgpro.c" linenumber="95" name="add_ln95" contextFuncName="blurf" moduleName="blurf" rtlName="add_ln95_fu_1028_p2" latency="0" BRAM="-1" DSP="-1" FF="0" LUT="21" fileDirectory="C:\Users\raoja\Desktop\uni\520"><\/item>
<item  id="63" filename="imageprosseing/imgpro.c" linenumber="95" name="sext_ln95_2" contextFuncName="blurf" moduleName="blurf" rtlName="sext_ln95_2_fu_1033_p1" latency="0" BRAM="-1" DSP="-1" FF="-1" LUT="-1" fileDirectory="C:\Users\raoja\Desktop\uni\520"><\/item>
<item  id="65" filename="imageprosseing/imgpro.c" linenumber="97" name="add_ln97" contextFuncName="blurf" moduleName="blurf" rtlName="add_ln97_fu_1038_p2" latency="0" BRAM="-1" DSP="-1" FF="0" LUT="21" fileDirectory="C:\Users\raoja\Desktop\uni\520"><\/item>
<item  id="66" filename="imageprosseing/imgpro.c" linenumber="97" name="sext_ln97" contextFuncName="blurf" moduleName="blurf" rtlName="sext_ln97_fu_1043_p1" latency="0" BRAM="-1" DSP="-1" FF="-1" LUT="-1" fileDirectory="C:\Users\raoja\Desktop\uni\520"><\/item>
<item  id="69" filename="imageprosseing/imgpro.c" linenumber="121" name="or_ln121" contextFuncName="blurf" moduleName="blurf" rtlName="or_ln121_fu_879_p2" latency="0" BRAM="-1" DSP="-1" FF="0" LUT="15" fileDirectory="C:\Users\raoja\Desktop\uni\520"><\/item>
<item  id="70" filename="imageprosseing/imgpro.c" linenumber="121" name="zext_ln121" contextFuncName="blurf" moduleName="blurf" rtlName="zext_ln121_fu_885_p1" latency="0" BRAM="-1" DSP="-1" FF="-1" LUT="-1" fileDirectory="C:\Users\raoja\Desktop\uni\520"><\/item>
<item  id="72" filename="imageprosseing/imgpro.c" linenumber="103" name="icmp_ln103_1" contextFuncName="blurf" moduleName="blurf" rtlName="icmp_ln103_1_fu_764_p2" latency="0" BRAM="-1" DSP="-1" FF="0" LUT="11" fileDirectory="C:\Users\raoja\Desktop\uni\520"><\/item>
<item  id="73" filename="imageprosseing/imgpro.c" linenumber="75" name="select_ln75_4" contextFuncName="blurf" moduleName="blurf" rtlName="select_ln75_4_fu_770_p3" latency="0" BRAM="-1" DSP="-1" FF="0" LUT="2" fileDirectory="C:\Users\raoja\Desktop\uni\520"><\/item>
<item  id="74" filename="imageprosseing/imgpro.c" linenumber="77" name="zext_ln77" contextFuncName="blurf" moduleName="blurf" rtlName="zext_ln77_fu_890_p1" latency="0" BRAM="-1" DSP="-1" FF="-1" LUT="-1" fileDirectory="C:\Users\raoja\Desktop\uni\520"><\/item>
<item  id="78" filename="imageprosseing/imgpro.c" linenumber="79" name="or_ln79" contextFuncName="blurf" moduleName="blurf" rtlName="or_ln79_fu_778_p2" latency="0" BRAM="-1" DSP="-1" FF="0" LUT="7" fileDirectory="C:\Users\raoja\Desktop\uni\520"><\/item>
<item  id="79" filename="imageprosseing/imgpro.c" linenumber="79" name="icmp_ln79" contextFuncName="blurf" moduleName="blurf" rtlName="icmp_ln79_fu_784_p2" latency="0" BRAM="-1" DSP="-1" FF="0" LUT="11" fileDirectory="C:\Users\raoja\Desktop\uni\520"><\/item>
<item  id="82" filename="imageprosseing/imgpro.c" linenumber="91" name="icmp_ln91_1" contextFuncName="blurf" moduleName="blurf" rtlName="icmp_ln91_1_fu_790_p2" latency="0" BRAM="-1" DSP="-1" FF="0" LUT="11" fileDirectory="C:\Users\raoja\Desktop\uni\520"><\/item>
<item  id="83" filename="imageprosseing/imgpro.c" linenumber="91" name="and_ln91" contextFuncName="blurf" moduleName="blurf" rtlName="and_ln91_fu_796_p2" latency="0" BRAM="-1" DSP="-1" FF="0" LUT="2" fileDirectory="C:\Users\raoja\Desktop\uni\520"><\/item>
<item  id="86" filename="imageprosseing/imgpro.c" linenumber="103" name="and_ln103" contextFuncName="blurf" moduleName="blurf" rtlName="and_ln103_fu_802_p2" latency="0" BRAM="-1" DSP="-1" FF="0" LUT="2" fileDirectory="C:\Users\raoja\Desktop\uni\520"><\/item>
<item  id="89" filename="imageprosseing/imgpro.c" linenumber="116" name="icmp_ln116" contextFuncName="blurf" moduleName="blurf" rtlName="icmp_ln116_fu_808_p2" latency="0" BRAM="-1" DSP="-1" FF="0" LUT="11" fileDirectory="C:\Users\raoja\Desktop\uni\520"><\/item>
<item  id="90" filename="imageprosseing/imgpro.c" linenumber="116" name="and_ln116" contextFuncName="blurf" moduleName="blurf" rtlName="and_ln116_fu_814_p2" latency="0" BRAM="-1" DSP="-1" FF="0" LUT="2" fileDirectory="C:\Users\raoja\Desktop\uni\520"><\/item>
<item  id="101" filename="imageprosseing/imgpro.c" linenumber="178" name="add_ln178" contextFuncName="blurf" moduleName="blurf" rtlName="grp_fu_484_p2" latency="0" BRAM="-1" DSP="-1" FF="0" LUT="15" fileDirectory="C:\Users\raoja\Desktop\uni\520"><\/item>
<item  id="102" filename="imageprosseing/imgpro.c" linenumber="178" name="zext_ln178" contextFuncName="blurf" moduleName="blurf" rtlName="zext_ln178_fu_1234_p1" latency="0" BRAM="-1" DSP="-1" FF="-1" LUT="-1" fileDirectory="C:\Users\raoja\Desktop\uni\520"><\/item>
<item  id="103" filename="imageprosseing/imgpro.c" linenumber="178" name="zext_ln178_1" contextFuncName="blurf" moduleName="blurf" rtlName="zext_ln178_1_fu_894_p1" latency="0" BRAM="-1" DSP="-1" FF="-1" LUT="-1" fileDirectory="C:\Users\raoja\Desktop\uni\520"><\/item>
<item  id="104" filename="imageprosseing/imgpro.c" linenumber="178" name="add_ln178_1" contextFuncName="blurf" moduleName="blurf" rtlName="add_ln178_1_fu_898_p2" latency="0" BRAM="-1" DSP="-1" FF="0" LUT="19" fileDirectory="C:\Users\raoja\Desktop\uni\520"><\/item>
<item  id="105" filename="imageprosseing/imgpro.c" linenumber="178" name="zext_ln178_2" contextFuncName="blurf" moduleName="blurf" rtlName="zext_ln178_2_fu_903_p1" latency="0" BRAM="-1" DSP="-1" FF="-1" LUT="-1" fileDirectory="C:\Users\raoja\Desktop\uni\520"><\/item>
<item  id="107" filename="imageprosseing/imgpro.c" linenumber="181" name="add_ln181" contextFuncName="blurf" moduleName="blurf" rtlName="add_ln181_fu_1238_p2" latency="0" BRAM="-1" DSP="-1" FF="0" LUT="21" fileDirectory="C:\Users\raoja\Desktop\uni\520"><\/item>
<item  id="108" filename="imageprosseing/imgpro.c" linenumber="181" name="sext_ln181" contextFuncName="blurf" moduleName="blurf" rtlName="sext_ln181_fu_1243_p1" latency="0" BRAM="-1" DSP="-1" FF="-1" LUT="-1" fileDirectory="C:\Users\raoja\Desktop\uni\520"><\/item>
<item  id="110" filename="imageprosseing/imgpro.c" linenumber="184" name="add_ln184" contextFuncName="blurf" moduleName="blurf" rtlName="add_ln184_fu_1048_p2" latency="0" BRAM="-1" DSP="-1" FF="0" LUT="19" fileDirectory="C:\Users\raoja\Desktop\uni\520"><\/item>
<item  id="111" filename="imageprosseing/imgpro.c" linenumber="184" name="zext_ln184" contextFuncName="blurf" moduleName="blurf" rtlName="zext_ln184_fu_1052_p1" latency="0" BRAM="-1" DSP="-1" FF="-1" LUT="-1" fileDirectory="C:\Users\raoja\Desktop\uni\520"><\/item>
<item  id="114" filename="imageprosseing/imgpro.c" linenumber="179" name="add_ln179" contextFuncName="blurf" moduleName="blurf" rtlName="grp_fu_489_p2" latency="0" BRAM="-1" DSP="-1" FF="0" LUT="15" fileDirectory="C:\Users\raoja\Desktop\uni\520"><\/item>
<item  id="115" filename="imageprosseing/imgpro.c" linenumber="179" name="sext_ln179" contextFuncName="blurf" moduleName="blurf" rtlName="sext_ln179_fu_908_p1" latency="0" BRAM="-1" DSP="-1" FF="-1" LUT="-1" fileDirectory="C:\Users\raoja\Desktop\uni\520"><\/item>
<item  id="116" filename="imageprosseing/imgpro.c" linenumber="179" name="add_ln179_1" contextFuncName="blurf" moduleName="blurf" rtlName="add_ln179_1_fu_912_p2" latency="0" BRAM="-1" DSP="-1" FF="0" LUT="21" fileDirectory="C:\Users\raoja\Desktop\uni\520"><\/item>
<item  id="117" filename="imageprosseing/imgpro.c" linenumber="179" name="sext_ln179_1" contextFuncName="blurf" moduleName="blurf" rtlName="sext_ln179_1_fu_917_p1" latency="0" BRAM="-1" DSP="-1" FF="-1" LUT="-1" fileDirectory="C:\Users\raoja\Desktop\uni\520"><\/item>
<item  id="119" filename="imageprosseing/imgpro.c" linenumber="182" name="add_ln182" contextFuncName="blurf" moduleName="blurf" rtlName="add_ln182_fu_1248_p2" latency="0" BRAM="-1" DSP="-1" FF="0" LUT="21" fileDirectory="C:\Users\raoja\Desktop\uni\520"><\/item>
<item  id="120" filename="imageprosseing/imgpro.c" linenumber="182" name="sext_ln182" contextFuncName="blurf" moduleName="blurf" rtlName="sext_ln182_fu_1369_p1" latency="0" BRAM="-1" DSP="-1" FF="-1" LUT="-1" fileDirectory="C:\Users\raoja\Desktop\uni\520"><\/item>
<item  id="122" filename="imageprosseing/imgpro.c" linenumber="185" name="add_ln185" contextFuncName="blurf" moduleName="blurf" rtlName="add_ln185_fu_1148_p2" latency="0" BRAM="-1" DSP="-1" FF="0" LUT="21" fileDirectory="C:\Users\raoja\Desktop\uni\520"><\/item>
<item  id="123" filename="imageprosseing/imgpro.c" linenumber="185" name="sext_ln185" contextFuncName="blurf" moduleName="blurf" rtlName="sext_ln185_fu_1152_p1" latency="0" BRAM="-1" DSP="-1" FF="-1" LUT="-1" fileDirectory="C:\Users\raoja\Desktop\uni\520"><\/item>
<item  id="126" filename="imageprosseing/imgpro.c" linenumber="180" name="zext_ln180" contextFuncName="blurf" moduleName="blurf" rtlName="zext_ln180_fu_1252_p1" latency="0" BRAM="-1" DSP="-1" FF="-1" LUT="-1" fileDirectory="C:\Users\raoja\Desktop\uni\520"><\/item>
<item  id="127" filename="imageprosseing/imgpro.c" linenumber="180" name="zext_ln180_1" contextFuncName="blurf" moduleName="blurf" rtlName="zext_ln180_1_fu_1057_p1" latency="0" BRAM="-1" DSP="-1" FF="-1" LUT="-1" fileDirectory="C:\Users\raoja\Desktop\uni\520"><\/item>
<item  id="128" filename="imageprosseing/imgpro.c" linenumber="180" name="add_ln180" contextFuncName="blurf" moduleName="blurf" rtlName="add_ln180_fu_1255_p2" latency="0" BRAM="-1" DSP="-1" FF="0" LUT="21" fileDirectory="C:\Users\raoja\Desktop\uni\520"><\/item>
<item  id="129" filename="imageprosseing/imgpro.c" linenumber="180" name="sext_ln180" contextFuncName="blurf" moduleName="blurf" rtlName="sext_ln180_fu_1260_p1" latency="0" BRAM="-1" DSP="-1" FF="-1" LUT="-1" fileDirectory="C:\Users\raoja\Desktop\uni\520"><\/item>
<item  id="131" filename="imageprosseing/imgpro.c" linenumber="183" name="add_ln183" contextFuncName="blurf" moduleName="blurf" rtlName="add_ln183_fu_1060_p2" latency="0" BRAM="-1" DSP="-1" FF="0" LUT="19" fileDirectory="C:\Users\raoja\Desktop\uni\520"><\/item>
<item  id="132" filename="imageprosseing/imgpro.c" linenumber="183" name="zext_ln183" contextFuncName="blurf" moduleName="blurf" rtlName="zext_ln183_fu_1065_p1" latency="0" BRAM="-1" DSP="-1" FF="-1" LUT="-1" fileDirectory="C:\Users\raoja\Desktop\uni\520"><\/item>
<item  id="134" filename="imageprosseing/imgpro.c" linenumber="186" name="add_ln186_8" contextFuncName="blurf" moduleName="blurf" rtlName="add_ln186_8_fu_1070_p2" latency="0" BRAM="-1" DSP="-1" FF="0" LUT="19" fileDirectory="C:\Users\raoja\Desktop\uni\520"><\/item>
<item  id="135" filename="imageprosseing/imgpro.c" linenumber="186" name="zext_ln186" contextFuncName="blurf" moduleName="blurf" rtlName="zext_ln186_fu_1157_p1" latency="0" BRAM="-1" DSP="-1" FF="-1" LUT="-1" fileDirectory="C:\Users\raoja\Desktop\uni\520"><\/item>
<item  id="145" filename="imageprosseing/imgpro.c" linenumber="186" name="add_ln186" contextFuncName="blurf" moduleName="blurf" rtlName="grp_fu_494_p2" latency="0" BRAM="-1" DSP="-1" FF="0" LUT="39" fileDirectory="C:\Users\raoja\Desktop\uni\520"><\/item>
<item  id="146" filename="imageprosseing/imgpro.c" linenumber="186" name="add_ln186_1" contextFuncName="blurf" moduleName="blurf" rtlName="grp_fu_500_p2" latency="0" BRAM="-1" DSP="-1" FF="0" LUT="39" fileDirectory="C:\Users\raoja\Desktop\uni\520"><\/item>
<item  id="147" filename="imageprosseing/imgpro.c" linenumber="186" name="add_ln186_2" contextFuncName="blurf" moduleName="blurf" rtlName="add_ln186_2_fu_1578_p2" latency="0" BRAM="-1" DSP="-1" FF="0" LUT="32" fileDirectory="C:\Users\raoja\Desktop\uni\520"><\/item>
<item  id="148" filename="imageprosseing/imgpro.c" linenumber="186" name="add_ln186_3" contextFuncName="blurf" moduleName="blurf" rtlName="add_ln186_3_fu_1481_p2" latency="0" BRAM="-1" DSP="-1" FF="0" LUT="32" fileDirectory="C:\Users\raoja\Desktop\uni\520"><\/item>
<item  id="149" filename="imageprosseing/imgpro.c" linenumber="186" name="add_ln186_4" contextFuncName="blurf" moduleName="blurf" rtlName="grp_fu_506_p2" latency="0" BRAM="-1" DSP="-1" FF="0" LUT="32" fileDirectory="C:\Users\raoja\Desktop\uni\520"><\/item>
<item  id="150" filename="imageprosseing/imgpro.c" linenumber="186" name="add_ln186_5" contextFuncName="blurf" moduleName="blurf" rtlName="add_ln186_5_fu_1265_p2" latency="0" BRAM="-1" DSP="-1" FF="0" LUT="32" fileDirectory="C:\Users\raoja\Desktop\uni\520"><\/item>
<item  id="151" filename="imageprosseing/imgpro.c" linenumber="186" name="add_ln186_6" contextFuncName="blurf" moduleName="blurf" rtlName="add_ln186_6_fu_1487_p2" latency="0" BRAM="-1" DSP="-1" FF="0" LUT="32" fileDirectory="C:\Users\raoja\Desktop\uni\520"><\/item>
<item  id="152" filename="imageprosseing/imgpro.c" linenumber="186" name="add_ln186_7" contextFuncName="blurf" moduleName="blurf" rtlName="add_ln186_7_fu_1584_p2" latency="0" BRAM="-1" DSP="-1" FF="0" LUT="32" fileDirectory="C:\Users\raoja\Desktop\uni\520"><\/item>
<item  id="154" filename="imageprosseing/imgpro.c" linenumber="186" name="mul_ln186" contextFuncName="blurf" moduleName="blurf" rtlName="mul_ln186_fu_1768_p2" latency="0" BRAM="-1" DSP="4" FF="0" LUT="22" fileDirectory="C:\Users\raoja\Desktop\uni\520"><\/item>
<item  id="155" filename="imageprosseing/imgpro.c" linenumber="186" name="sub_ln186" contextFuncName="blurf" moduleName="blurf" rtlName="sub_ln186_fu_1784_p2" latency="0" BRAM="-1" DSP="-1" FF="0" LUT="72" fileDirectory="C:\Users\raoja\Desktop\uni\520"><\/item>
<item  id="156" filename="imageprosseing/imgpro.c" linenumber="186" name="tmp_35" contextFuncName="blurf" moduleName="blurf" rtlName="tmp_35_reg_2377" latency="0" BRAM="-1" DSP="-1" FF="-1" LUT="-1" fileDirectory="C:\Users\raoja\Desktop\uni\520"><\/item>
<item  id="157" filename="imageprosseing/imgpro.c" linenumber="186" name="tmp_36" contextFuncName="blurf" moduleName="blurf" rtlName="tmp_36_fu_1789_p4" latency="0" BRAM="-1" DSP="-1" FF="-1" LUT="-1" fileDirectory="C:\Users\raoja\Desktop\uni\520"><\/item>
<item  id="158" filename="imageprosseing/imgpro.c" linenumber="186" name="sext_ln186_1" contextFuncName="blurf" moduleName="blurf" rtlName="sext_ln186_1_fu_1799_p1" latency="0" BRAM="-1" DSP="-1" FF="-1" LUT="-1" fileDirectory="C:\Users\raoja\Desktop\uni\520"><\/item>
<item  id="159" filename="imageprosseing/imgpro.c" linenumber="186" name="tmp_37" contextFuncName="blurf" moduleName="blurf" rtlName="tmp_37_reg_2408" latency="0" BRAM="-1" DSP="-1" FF="-1" LUT="-1" fileDirectory="C:\Users\raoja\Desktop\uni\520"><\/item>
<item  id="160" filename="imageprosseing/imgpro.c" linenumber="186" name="sext_ln186_2" contextFuncName="blurf" moduleName="blurf" rtlName="sext_ln186_2_fu_1803_p1" latency="0" BRAM="-1" DSP="-1" FF="-1" LUT="-1" fileDirectory="C:\Users\raoja\Desktop\uni\520"><\/item>
<item  id="161" filename="imageprosseing/imgpro.c" linenumber="186" name="select_ln186" contextFuncName="blurf" moduleName="blurf" rtlName="select_ln186_fu_1806_p3" latency="0" BRAM="-1" DSP="-1" FF="0" LUT="32" fileDirectory="C:\Users\raoja\Desktop\uni\520"><\/item>
<item  id="162" filename="imageprosseing/imgpro.c" linenumber="186" name="sub_ln186_1" contextFuncName="blurf" moduleName="blurf" rtlName="sub_ln186_1_fu_1813_p2" latency="0" BRAM="-1" DSP="-1" FF="0" LUT="39" fileDirectory="C:\Users\raoja\Desktop\uni\520"><\/item>
<item  id="163" filename="imageprosseing/imgpro.c" linenumber="186" name="select_ln186_1" contextFuncName="blurf" moduleName="blurf" rtlName="select_ln186_1_fu_1819_p3" latency="0" BRAM="-1" DSP="-1" FF="0" LUT="32" fileDirectory="C:\Users\raoja\Desktop\uni\520"><\/item>
<item  id="167" filename="imageprosseing/imgpro.c" linenumber="166" name="add_ln166" contextFuncName="blurf" moduleName="blurf" rtlName="grp_fu_489_p2" latency="0" BRAM="-1" DSP="-1" FF="0" LUT="15" fileDirectory="C:\Users\raoja\Desktop\uni\520"><\/item>
<item  id="168" filename="imageprosseing/imgpro.c" linenumber="166" name="sext_ln166" contextFuncName="blurf" moduleName="blurf" rtlName="sext_ln166_fu_1161_p1" latency="0" BRAM="-1" DSP="-1" FF="-1" LUT="-1" fileDirectory="C:\Users\raoja\Desktop\uni\520"><\/item>
<item  id="169" filename="imageprosseing/imgpro.c" linenumber="166" name="add_ln166_1" contextFuncName="blurf" moduleName="blurf" rtlName="add_ln166_1_fu_1165_p2" latency="0" BRAM="-1" DSP="-1" FF="0" LUT="21" fileDirectory="C:\Users\raoja\Desktop\uni\520"><\/item>
<item  id="170" filename="imageprosseing/imgpro.c" linenumber="166" name="sext_ln166_1" contextFuncName="blurf" moduleName="blurf" rtlName="sext_ln166_1_fu_1170_p1" latency="0" BRAM="-1" DSP="-1" FF="-1" LUT="-1" fileDirectory="C:\Users\raoja\Desktop\uni\520"><\/item>
<item  id="172" filename="imageprosseing/imgpro.c" linenumber="170" name="add_ln170" contextFuncName="blurf" moduleName="blurf" rtlName="add_ln170_fu_1175_p2" latency="0" BRAM="-1" DSP="-1" FF="0" LUT="21" fileDirectory="C:\Users\raoja\Desktop\uni\520"><\/item>
<item  id="173" filename="imageprosseing/imgpro.c" linenumber="170" name="sext_ln170" contextFuncName="blurf" moduleName="blurf" rtlName="sext_ln170_fu_1180_p1" latency="0" BRAM="-1" DSP="-1" FF="-1" LUT="-1" fileDirectory="C:\Users\raoja\Desktop\uni\520"><\/item>
<item  id="176" filename="imageprosseing/imgpro.c" linenumber="168" name="zext_ln168" contextFuncName="blurf" moduleName="blurf" rtlName="zext_ln168_fu_1075_p1" latency="0" BRAM="-1" DSP="-1" FF="-1" LUT="-1" fileDirectory="C:\Users\raoja\Desktop\uni\520"><\/item>
<item  id="177" filename="imageprosseing/imgpro.c" linenumber="168" name="zext_ln168_1" contextFuncName="blurf" moduleName="blurf" rtlName="zext_ln168_1_fu_922_p1" latency="0" BRAM="-1" DSP="-1" FF="-1" LUT="-1" fileDirectory="C:\Users\raoja\Desktop\uni\520"><\/item>
<item  id="178" filename="imageprosseing/imgpro.c" linenumber="168" name="add_ln168" contextFuncName="blurf" moduleName="blurf" rtlName="add_ln168_fu_1078_p2" latency="0" BRAM="-1" DSP="-1" FF="0" LUT="21" fileDirectory="C:\Users\raoja\Desktop\uni\520"><\/item>
<item  id="179" filename="imageprosseing/imgpro.c" linenumber="168" name="sext_ln168" contextFuncName="blurf" moduleName="blurf" rtlName="sext_ln168_fu_1083_p1" latency="0" BRAM="-1" DSP="-1" FF="-1" LUT="-1" fileDirectory="C:\Users\raoja\Desktop\uni\520"><\/item>
<item  id="181" filename="imageprosseing/imgpro.c" linenumber="174" name="add_ln174_5" contextFuncName="blurf" moduleName="blurf" rtlName="add_ln174_5_fu_925_p2" latency="0" BRAM="-1" DSP="-1" FF="0" LUT="19" fileDirectory="C:\Users\raoja\Desktop\uni\520"><\/item>
<item  id="182" filename="imageprosseing/imgpro.c" linenumber="174" name="zext_ln174" contextFuncName="blurf" moduleName="blurf" rtlName="zext_ln174_fu_930_p1" latency="0" BRAM="-1" DSP="-1" FF="-1" LUT="-1" fileDirectory="C:\Users\raoja\Desktop\uni\520"><\/item>
<item  id="186" filename="imageprosseing/imgpro.c" linenumber="169" name="add_ln169" contextFuncName="blurf" moduleName="blurf" rtlName="grp_fu_484_p2" latency="0" BRAM="-1" DSP="-1" FF="0" LUT="15" fileDirectory="C:\Users\raoja\Desktop\uni\520"><\/item>
<item  id="187" filename="imageprosseing/imgpro.c" linenumber="169" name="zext_ln169" contextFuncName="blurf" moduleName="blurf" rtlName="zext_ln169_fu_1088_p1" latency="0" BRAM="-1" DSP="-1" FF="-1" LUT="-1" fileDirectory="C:\Users\raoja\Desktop\uni\520"><\/item>
<item  id="188" filename="imageprosseing/imgpro.c" linenumber="169" name="zext_ln169_1" contextFuncName="blurf" moduleName="blurf" rtlName="zext_ln169_1_fu_935_p1" latency="0" BRAM="-1" DSP="-1" FF="-1" LUT="-1" fileDirectory="C:\Users\raoja\Desktop\uni\520"><\/item>
<item  id="189" filename="imageprosseing/imgpro.c" linenumber="169" name="add_ln169_1" contextFuncName="blurf" moduleName="blurf" rtlName="add_ln169_1_fu_1092_p2" latency="0" BRAM="-1" DSP="-1" FF="0" LUT="21" fileDirectory="C:\Users\raoja\Desktop\uni\520"><\/item>
<item  id="190" filename="imageprosseing/imgpro.c" linenumber="169" name="sext_ln169" contextFuncName="blurf" moduleName="blurf" rtlName="sext_ln169_fu_1097_p1" latency="0" BRAM="-1" DSP="-1" FF="-1" LUT="-1" fileDirectory="C:\Users\raoja\Desktop\uni\520"><\/item>
<item  id="192" filename="imageprosseing/imgpro.c" linenumber="173" name="add_ln173" contextFuncName="blurf" moduleName="blurf" rtlName="add_ln173_fu_939_p2" latency="0" BRAM="-1" DSP="-1" FF="0" LUT="19" fileDirectory="C:\Users\raoja\Desktop\uni\520"><\/item>
<item  id="193" filename="imageprosseing/imgpro.c" linenumber="173" name="zext_ln173" contextFuncName="blurf" moduleName="blurf" rtlName="zext_ln173_fu_944_p1" latency="0" BRAM="-1" DSP="-1" FF="-1" LUT="-1" fileDirectory="C:\Users\raoja\Desktop\uni\520"><\/item>
<item  id="199" filename="imageprosseing/imgpro.c" linenumber="174" name="add_ln174" contextFuncName="blurf" moduleName="blurf" rtlName="grp_fu_500_p2" latency="0" BRAM="-1" DSP="-1" FF="0" LUT="39" fileDirectory="C:\Users\raoja\Desktop\uni\520"><\/item>
<item  id="200" filename="imageprosseing/imgpro.c" linenumber="174" name="add_ln174_1" contextFuncName="blurf" moduleName="blurf" rtlName="add_ln174_1_fu_1373_p2" latency="0" BRAM="-1" DSP="-1" FF="0" LUT="32" fileDirectory="C:\Users\raoja\Desktop\uni\520"><\/item>
<item  id="201" filename="imageprosseing/imgpro.c" linenumber="174" name="add_ln174_2" contextFuncName="blurf" moduleName="blurf" rtlName="add_ln174_2_fu_1271_p2" latency="0" BRAM="-1" DSP="-1" FF="0" LUT="32" fileDirectory="C:\Users\raoja\Desktop\uni\520"><\/item>
<item  id="202" filename="imageprosseing/imgpro.c" linenumber="174" name="add_ln174_3" contextFuncName="blurf" moduleName="blurf" rtlName="add_ln174_3_fu_1277_p2" latency="0" BRAM="-1" DSP="-1" FF="0" LUT="32" fileDirectory="C:\Users\raoja\Desktop\uni\520"><\/item>
<item  id="203" filename="imageprosseing/imgpro.c" linenumber="174" name="add_ln174_4" contextFuncName="blurf" moduleName="blurf" rtlName="add_ln174_4_fu_1379_p2" latency="0" BRAM="-1" DSP="-1" FF="0" LUT="32" fileDirectory="C:\Users\raoja\Desktop\uni\520"><\/item>
<item  id="205" filename="imageprosseing/imgpro.c" linenumber="174" name="mul_ln174" contextFuncName="blurf" moduleName="blurf" rtlName="mul_ln174_fu_1495_p2" latency="0" BRAM="-1" DSP="4" FF="0" LUT="22" fileDirectory="C:\Users\raoja\Desktop\uni\520"><\/item>
<item  id="206" filename="imageprosseing/imgpro.c" linenumber="174" name="sub_ln174" contextFuncName="blurf" moduleName="blurf" rtlName="sub_ln174_fu_1597_p2" latency="0" BRAM="-1" DSP="-1" FF="0" LUT="72" fileDirectory="C:\Users\raoja\Desktop\uni\520"><\/item>
<item  id="207" filename="imageprosseing/imgpro.c" linenumber="174" name="tmp_32" contextFuncName="blurf" moduleName="blurf" rtlName="tmp_32_reg_2293" latency="0" BRAM="-1" DSP="-1" FF="-1" LUT="-1" fileDirectory="C:\Users\raoja\Desktop\uni\520"><\/item>
<item  id="208" filename="imageprosseing/imgpro.c" linenumber="174" name="tmp_33" contextFuncName="blurf" moduleName="blurf" rtlName="tmp_33_fu_1602_p4" latency="0" BRAM="-1" DSP="-1" FF="-1" LUT="-1" fileDirectory="C:\Users\raoja\Desktop\uni\520"><\/item>
<item  id="209" filename="imageprosseing/imgpro.c" linenumber="174" name="sext_ln174_1" contextFuncName="blurf" moduleName="blurf" rtlName="sext_ln174_1_fu_1612_p1" latency="0" BRAM="-1" DSP="-1" FF="-1" LUT="-1" fileDirectory="C:\Users\raoja\Desktop\uni\520"><\/item>
<item  id="210" filename="imageprosseing/imgpro.c" linenumber="174" name="tmp_34" contextFuncName="blurf" moduleName="blurf" rtlName="tmp_34_reg_2337" latency="0" BRAM="-1" DSP="-1" FF="-1" LUT="-1" fileDirectory="C:\Users\raoja\Desktop\uni\520"><\/item>
<item  id="211" filename="imageprosseing/imgpro.c" linenumber="174" name="sext_ln174_2" contextFuncName="blurf" moduleName="blurf" rtlName="sext_ln174_2_fu_1616_p1" latency="0" BRAM="-1" DSP="-1" FF="-1" LUT="-1" fileDirectory="C:\Users\raoja\Desktop\uni\520"><\/item>
<item  id="212" filename="imageprosseing/imgpro.c" linenumber="174" name="select_ln174" contextFuncName="blurf" moduleName="blurf" rtlName="select_ln174_fu_1619_p3" latency="0" BRAM="-1" DSP="-1" FF="0" LUT="32" fileDirectory="C:\Users\raoja\Desktop\uni\520"><\/item>
<item  id="213" filename="imageprosseing/imgpro.c" linenumber="174" name="sub_ln174_1" contextFuncName="blurf" moduleName="blurf" rtlName="sub_ln174_1_fu_1626_p2" latency="0" BRAM="-1" DSP="-1" FF="0" LUT="39" fileDirectory="C:\Users\raoja\Desktop\uni\520"><\/item>
<item  id="214" filename="imageprosseing/imgpro.c" linenumber="174" name="select_ln174_1" contextFuncName="blurf" moduleName="blurf" rtlName="select_ln174_1_fu_1632_p3" latency="0" BRAM="-1" DSP="-1" FF="0" LUT="32" fileDirectory="C:\Users\raoja\Desktop\uni\520"><\/item>
<item  id="220" filename="imageprosseing/imgpro.c" linenumber="154" name="add_ln154" contextFuncName="blurf" moduleName="blurf" rtlName="grp_fu_489_p2" latency="0" BRAM="-1" DSP="-1" FF="0" LUT="15" fileDirectory="C:\Users\raoja\Desktop\uni\520"><\/item>
<item  id="221" filename="imageprosseing/imgpro.c" linenumber="154" name="sext_ln154" contextFuncName="blurf" moduleName="blurf" rtlName="sext_ln154_fu_949_p1" latency="0" BRAM="-1" DSP="-1" FF="-1" LUT="-1" fileDirectory="C:\Users\raoja\Desktop\uni\520"><\/item>
<item  id="222" filename="imageprosseing/imgpro.c" linenumber="154" name="add_ln154_1" contextFuncName="blurf" moduleName="blurf" rtlName="add_ln154_1_fu_1185_p2" latency="0" BRAM="-1" DSP="-1" FF="0" LUT="21" fileDirectory="C:\Users\raoja\Desktop\uni\520"><\/item>
<item  id="223" filename="imageprosseing/imgpro.c" linenumber="154" name="sext_ln154_1" contextFuncName="blurf" moduleName="blurf" rtlName="sext_ln154_1_fu_1189_p1" latency="0" BRAM="-1" DSP="-1" FF="-1" LUT="-1" fileDirectory="C:\Users\raoja\Desktop\uni\520"><\/item>
<item  id="225" filename="imageprosseing/imgpro.c" linenumber="155" name="add_ln155" contextFuncName="blurf" moduleName="blurf" rtlName="add_ln155_fu_953_p2" latency="0" BRAM="-1" DSP="-1" FF="0" LUT="21" fileDirectory="C:\Users\raoja\Desktop\uni\520"><\/item>
<item  id="226" filename="imageprosseing/imgpro.c" linenumber="155" name="sext_ln155" contextFuncName="blurf" moduleName="blurf" rtlName="sext_ln155_fu_958_p1" latency="0" BRAM="-1" DSP="-1" FF="-1" LUT="-1" fileDirectory="C:\Users\raoja\Desktop\uni\520"><\/item>
<item  id="230" filename="imageprosseing/imgpro.c" linenumber="159" name="zext_ln159" contextFuncName="blurf" moduleName="blurf" rtlName="zext_ln159_fu_963_p1" latency="0" BRAM="-1" DSP="-1" FF="-1" LUT="-1" fileDirectory="C:\Users\raoja\Desktop\uni\520"><\/item>
<item  id="231" filename="imageprosseing/imgpro.c" linenumber="159" name="add_ln159" contextFuncName="blurf" moduleName="blurf" rtlName="add_ln159_fu_966_p2" latency="0" BRAM="-1" DSP="-1" FF="0" LUT="19" fileDirectory="C:\Users\raoja\Desktop\uni\520"><\/item>
<item  id="232" filename="imageprosseing/imgpro.c" linenumber="159" name="zext_ln159_1" contextFuncName="blurf" moduleName="blurf" rtlName="zext_ln159_1_fu_971_p1" latency="0" BRAM="-1" DSP="-1" FF="-1" LUT="-1" fileDirectory="C:\Users\raoja\Desktop\uni\520"><\/item>
<item  id="234" filename="imageprosseing/imgpro.c" linenumber="162" name="add_ln162_5" contextFuncName="blurf" moduleName="blurf" rtlName="add_ln162_5_fu_1102_p2" latency="0" BRAM="-1" DSP="-1" FF="0" LUT="19" fileDirectory="C:\Users\raoja\Desktop\uni\520"><\/item>
<item  id="235" filename="imageprosseing/imgpro.c" linenumber="162" name="zext_ln162" contextFuncName="blurf" moduleName="blurf" rtlName="zext_ln162_fu_1194_p1" latency="0" BRAM="-1" DSP="-1" FF="-1" LUT="-1" fileDirectory="C:\Users\raoja\Desktop\uni\520"><\/item>
<item  id="239" filename="imageprosseing/imgpro.c" linenumber="160" name="add_ln160" contextFuncName="blurf" moduleName="blurf" rtlName="grp_fu_484_p2" latency="0" BRAM="-1" DSP="-1" FF="0" LUT="15" fileDirectory="C:\Users\raoja\Desktop\uni\520"><\/item>
<item  id="240" filename="imageprosseing/imgpro.c" linenumber="160" name="zext_ln160" contextFuncName="blurf" moduleName="blurf" rtlName="zext_ln160_fu_1106_p1" latency="0" BRAM="-1" DSP="-1" FF="-1" LUT="-1" fileDirectory="C:\Users\raoja\Desktop\uni\520"><\/item>
<item  id="241" filename="imageprosseing/imgpro.c" linenumber="160" name="add_ln160_1" contextFuncName="blurf" moduleName="blurf" rtlName="add_ln160_1_fu_1110_p2" latency="0" BRAM="-1" DSP="-1" FF="0" LUT="19" fileDirectory="C:\Users\raoja\Desktop\uni\520"><\/item>
<item  id="242" filename="imageprosseing/imgpro.c" linenumber="160" name="zext_ln160_1" contextFuncName="blurf" moduleName="blurf" rtlName="zext_ln160_1_fu_1115_p1" latency="0" BRAM="-1" DSP="-1" FF="-1" LUT="-1" fileDirectory="C:\Users\raoja\Desktop\uni\520"><\/item>
<item  id="244" filename="imageprosseing/imgpro.c" linenumber="161" name="add_ln161" contextFuncName="blurf" moduleName="blurf" rtlName="add_ln161_fu_1120_p2" latency="0" BRAM="-1" DSP="-1" FF="0" LUT="19" fileDirectory="C:\Users\raoja\Desktop\uni\520"><\/item>
<item  id="245" filename="imageprosseing/imgpro.c" linenumber="161" name="zext_ln161" contextFuncName="blurf" moduleName="blurf" rtlName="zext_ln161_fu_1125_p1" latency="0" BRAM="-1" DSP="-1" FF="-1" LUT="-1" fileDirectory="C:\Users\raoja\Desktop\uni\520"><\/item>
<item  id="250" filename="imageprosseing/imgpro.c" linenumber="162" name="add_ln162" contextFuncName="blurf" moduleName="blurf" rtlName="grp_fu_494_p2" latency="0" BRAM="-1" DSP="-1" FF="0" LUT="39" fileDirectory="C:\Users\raoja\Desktop\uni\520"><\/item>
<item  id="251" filename="imageprosseing/imgpro.c" linenumber="162" name="add_ln162_1" contextFuncName="blurf" moduleName="blurf" rtlName="grp_fu_566_p2" latency="0" BRAM="-1" DSP="-1" FF="0" LUT="32" fileDirectory="C:\Users\raoja\Desktop\uni\520"><\/item>
<item  id="252" filename="imageprosseing/imgpro.c" linenumber="162" name="add_ln162_2" contextFuncName="blurf" moduleName="blurf" rtlName="grp_fu_548_p2" latency="0" BRAM="-1" DSP="-1" FF="0" LUT="32" fileDirectory="C:\Users\raoja\Desktop\uni\520"><\/item>
<item  id="253" filename="imageprosseing/imgpro.c" linenumber="162" name="add_ln162_3" contextFuncName="blurf" moduleName="blurf" rtlName="grp_fu_554_p2" latency="0" BRAM="-1" DSP="-1" FF="0" LUT="32" fileDirectory="C:\Users\raoja\Desktop\uni\520"><\/item>
<item  id="254" filename="imageprosseing/imgpro.c" linenumber="162" name="add_ln162_4" contextFuncName="blurf" moduleName="blurf" rtlName="grp_fu_620_p2" latency="0" BRAM="-1" DSP="-1" FF="0" LUT="32" fileDirectory="C:\Users\raoja\Desktop\uni\520"><\/item>
<item  id="256" filename="imageprosseing/imgpro.c" linenumber="162" name="mul_ln162" contextFuncName="blurf" moduleName="blurf" rtlName="mul_ln162_fu_1515_p2" latency="0" BRAM="-1" DSP="4" FF="0" LUT="22" fileDirectory="C:\Users\raoja\Desktop\uni\520"><\/item>
<item  id="257" filename="imageprosseing/imgpro.c" linenumber="162" name="sub_ln162" contextFuncName="blurf" moduleName="blurf" rtlName="sub_ln162_fu_1639_p2" latency="0" BRAM="-1" DSP="-1" FF="0" LUT="72" fileDirectory="C:\Users\raoja\Desktop\uni\520"><\/item>
<item  id="258" filename="imageprosseing/imgpro.c" linenumber="162" name="tmp_29" contextFuncName="blurf" moduleName="blurf" rtlName="tmp_29_reg_2299" latency="0" BRAM="-1" DSP="-1" FF="-1" LUT="-1" fileDirectory="C:\Users\raoja\Desktop\uni\520"><\/item>
<item  id="259" filename="imageprosseing/imgpro.c" linenumber="162" name="tmp_30" contextFuncName="blurf" moduleName="blurf" rtlName="tmp_30_fu_1644_p4" latency="0" BRAM="-1" DSP="-1" FF="-1" LUT="-1" fileDirectory="C:\Users\raoja\Desktop\uni\520"><\/item>
<item  id="260" filename="imageprosseing/imgpro.c" linenumber="162" name="sext_ln162_1" contextFuncName="blurf" moduleName="blurf" rtlName="sext_ln162_1_fu_1654_p1" latency="0" BRAM="-1" DSP="-1" FF="-1" LUT="-1" fileDirectory="C:\Users\raoja\Desktop\uni\520"><\/item>
<item  id="261" filename="imageprosseing/imgpro.c" linenumber="162" name="tmp_31" contextFuncName="blurf" moduleName="blurf" rtlName="tmp_31_reg_2347" latency="0" BRAM="-1" DSP="-1" FF="-1" LUT="-1" fileDirectory="C:\Users\raoja\Desktop\uni\520"><\/item>
<item  id="262" filename="imageprosseing/imgpro.c" linenumber="162" name="sext_ln162_2" contextFuncName="blurf" moduleName="blurf" rtlName="sext_ln162_2_fu_1658_p1" latency="0" BRAM="-1" DSP="-1" FF="-1" LUT="-1" fileDirectory="C:\Users\raoja\Desktop\uni\520"><\/item>
<item  id="263" filename="imageprosseing/imgpro.c" linenumber="162" name="select_ln162" contextFuncName="blurf" moduleName="blurf" rtlName="select_ln162_fu_1661_p3" latency="0" BRAM="-1" DSP="-1" FF="0" LUT="32" fileDirectory="C:\Users\raoja\Desktop\uni\520"><\/item>
<item  id="264" filename="imageprosseing/imgpro.c" linenumber="162" name="sub_ln162_1" contextFuncName="blurf" moduleName="blurf" rtlName="sub_ln162_1_fu_1668_p2" latency="0" BRAM="-1" DSP="-1" FF="0" LUT="39" fileDirectory="C:\Users\raoja\Desktop\uni\520"><\/item>
<item  id="265" filename="imageprosseing/imgpro.c" linenumber="162" name="select_ln162_1" contextFuncName="blurf" moduleName="blurf" rtlName="select_ln162_1_fu_1674_p3" latency="0" BRAM="-1" DSP="-1" FF="0" LUT="32" fileDirectory="C:\Users\raoja\Desktop\uni\520"><\/item>
<item  id="277" filename="imageprosseing/imgpro.c" linenumber="150" name="add_ln150" contextFuncName="blurf" moduleName="blurf" rtlName="grp_fu_494_p2" latency="0" BRAM="-1" DSP="-1" FF="0" LUT="39" fileDirectory="C:\Users\raoja\Desktop\uni\520"><\/item>
<item  id="278" filename="imageprosseing/imgpro.c" linenumber="150" name="add_ln150_1" contextFuncName="blurf" moduleName="blurf" rtlName="grp_fu_566_p2" latency="0" BRAM="-1" DSP="-1" FF="0" LUT="32" fileDirectory="C:\Users\raoja\Desktop\uni\520"><\/item>
<item  id="279" filename="imageprosseing/imgpro.c" linenumber="150" name="add_ln150_2" contextFuncName="blurf" moduleName="blurf" rtlName="grp_fu_548_p2" latency="0" BRAM="-1" DSP="-1" FF="0" LUT="32" fileDirectory="C:\Users\raoja\Desktop\uni\520"><\/item>
<item  id="280" filename="imageprosseing/imgpro.c" linenumber="150" name="add_ln150_3" contextFuncName="blurf" moduleName="blurf" rtlName="grp_fu_554_p2" latency="0" BRAM="-1" DSP="-1" FF="0" LUT="32" fileDirectory="C:\Users\raoja\Desktop\uni\520"><\/item>
<item  id="281" filename="imageprosseing/imgpro.c" linenumber="150" name="add_ln150_4" contextFuncName="blurf" moduleName="blurf" rtlName="grp_fu_620_p2" latency="0" BRAM="-1" DSP="-1" FF="0" LUT="32" fileDirectory="C:\Users\raoja\Desktop\uni\520"><\/item>
<item  id="283" filename="imageprosseing/imgpro.c" linenumber="150" name="mul_ln150" contextFuncName="blurf" moduleName="blurf" rtlName="mul_ln150_fu_1535_p2" latency="0" BRAM="-1" DSP="4" FF="0" LUT="22" fileDirectory="C:\Users\raoja\Desktop\uni\520"><\/item>
<item  id="284" filename="imageprosseing/imgpro.c" linenumber="150" name="sub_ln150" contextFuncName="blurf" moduleName="blurf" rtlName="sub_ln150_fu_1681_p2" latency="0" BRAM="-1" DSP="-1" FF="0" LUT="72" fileDirectory="C:\Users\raoja\Desktop\uni\520"><\/item>
<item  id="285" filename="imageprosseing/imgpro.c" linenumber="150" name="tmp_26" contextFuncName="blurf" moduleName="blurf" rtlName="tmp_29_reg_2299" latency="0" BRAM="-1" DSP="-1" FF="-1" LUT="-1" fileDirectory="C:\Users\raoja\Desktop\uni\520"><\/item>
<item  id="286" filename="imageprosseing/imgpro.c" linenumber="150" name="tmp_27" contextFuncName="blurf" moduleName="blurf" rtlName="tmp_27_fu_1686_p4" latency="0" BRAM="-1" DSP="-1" FF="-1" LUT="-1" fileDirectory="C:\Users\raoja\Desktop\uni\520"><\/item>
<item  id="287" filename="imageprosseing/imgpro.c" linenumber="150" name="sext_ln150_1" contextFuncName="blurf" moduleName="blurf" rtlName="sext_ln150_1_fu_1696_p1" latency="0" BRAM="-1" DSP="-1" FF="-1" LUT="-1" fileDirectory="C:\Users\raoja\Desktop\uni\520"><\/item>
<item  id="288" filename="imageprosseing/imgpro.c" linenumber="150" name="tmp_28" contextFuncName="blurf" moduleName="blurf" rtlName="tmp_28_reg_2357" latency="0" BRAM="-1" DSP="-1" FF="-1" LUT="-1" fileDirectory="C:\Users\raoja\Desktop\uni\520"><\/item>
<item  id="289" filename="imageprosseing/imgpro.c" linenumber="150" name="sext_ln150_2" contextFuncName="blurf" moduleName="blurf" rtlName="sext_ln150_2_fu_1700_p1" latency="0" BRAM="-1" DSP="-1" FF="-1" LUT="-1" fileDirectory="C:\Users\raoja\Desktop\uni\520"><\/item>
<item  id="290" filename="imageprosseing/imgpro.c" linenumber="150" name="select_ln150" contextFuncName="blurf" moduleName="blurf" rtlName="select_ln150_fu_1703_p3" latency="0" BRAM="-1" DSP="-1" FF="0" LUT="32" fileDirectory="C:\Users\raoja\Desktop\uni\520"><\/item>
<item  id="291" filename="imageprosseing/imgpro.c" linenumber="150" name="sub_ln150_1" contextFuncName="blurf" moduleName="blurf" rtlName="sub_ln150_1_fu_1710_p2" latency="0" BRAM="-1" DSP="-1" FF="0" LUT="39" fileDirectory="C:\Users\raoja\Desktop\uni\520"><\/item>
<item  id="292" filename="imageprosseing/imgpro.c" linenumber="150" name="select_ln150_1" contextFuncName="blurf" moduleName="blurf" rtlName="select_ln150_1_fu_1716_p3" latency="0" BRAM="-1" DSP="-1" FF="0" LUT="32" fileDirectory="C:\Users\raoja\Desktop\uni\520"><\/item>
<item  id="304" filename="imageprosseing/imgpro.c" linenumber="138" name="add_ln138" contextFuncName="blurf" moduleName="blurf" rtlName="add_ln138_fu_1198_p2" latency="0" BRAM="-1" DSP="-1" FF="0" LUT="39" fileDirectory="C:\Users\raoja\Desktop\uni\520"><\/item>
<item  id="305" filename="imageprosseing/imgpro.c" linenumber="138" name="add_ln138_1" contextFuncName="blurf" moduleName="blurf" rtlName="add_ln138_1_fu_1392_p2" latency="0" BRAM="-1" DSP="-1" FF="0" LUT="32" fileDirectory="C:\Users\raoja\Desktop\uni\520"><\/item>
<item  id="306" filename="imageprosseing/imgpro.c" linenumber="138" name="add_ln138_2" contextFuncName="blurf" moduleName="blurf" rtlName="grp_fu_560_p2" latency="0" BRAM="-1" DSP="-1" FF="0" LUT="32" fileDirectory="C:\Users\raoja\Desktop\uni\520"><\/item>
<item  id="307" filename="imageprosseing/imgpro.c" linenumber="138" name="add_ln138_3" contextFuncName="blurf" moduleName="blurf" rtlName="add_ln138_3_fu_1283_p2" latency="0" BRAM="-1" DSP="-1" FF="0" LUT="32" fileDirectory="C:\Users\raoja\Desktop\uni\520"><\/item>
<item  id="308" filename="imageprosseing/imgpro.c" linenumber="138" name="add_ln138_4" contextFuncName="blurf" moduleName="blurf" rtlName="add_ln138_4_fu_1397_p2" latency="0" BRAM="-1" DSP="-1" FF="0" LUT="32" fileDirectory="C:\Users\raoja\Desktop\uni\520"><\/item>
<item  id="310" filename="imageprosseing/imgpro.c" linenumber="138" name="mul_ln138" contextFuncName="blurf" moduleName="blurf" rtlName="mul_ln138_fu_1554_p2" latency="0" BRAM="-1" DSP="4" FF="0" LUT="22" fileDirectory="C:\Users\raoja\Desktop\uni\520"><\/item>
<item  id="311" filename="imageprosseing/imgpro.c" linenumber="138" name="sub_ln138" contextFuncName="blurf" moduleName="blurf" rtlName="sub_ln138_fu_1723_p2" latency="0" BRAM="-1" DSP="-1" FF="0" LUT="72" fileDirectory="C:\Users\raoja\Desktop\uni\520"><\/item>
<item  id="312" filename="imageprosseing/imgpro.c" linenumber="138" name="tmp_23" contextFuncName="blurf" moduleName="blurf" rtlName="tmp_23_reg_2316" latency="0" BRAM="-1" DSP="-1" FF="-1" LUT="-1" fileDirectory="C:\Users\raoja\Desktop\uni\520"><\/item>
<item  id="313" filename="imageprosseing/imgpro.c" linenumber="138" name="tmp_24" contextFuncName="blurf" moduleName="blurf" rtlName="tmp_24_fu_1728_p4" latency="0" BRAM="-1" DSP="-1" FF="-1" LUT="-1" fileDirectory="C:\Users\raoja\Desktop\uni\520"><\/item>
<item  id="314" filename="imageprosseing/imgpro.c" linenumber="138" name="sext_ln138_1" contextFuncName="blurf" moduleName="blurf" rtlName="sext_ln138_1_fu_1738_p1" latency="0" BRAM="-1" DSP="-1" FF="-1" LUT="-1" fileDirectory="C:\Users\raoja\Desktop\uni\520"><\/item>
<item  id="315" filename="imageprosseing/imgpro.c" linenumber="138" name="tmp_25" contextFuncName="blurf" moduleName="blurf" rtlName="tmp_25_reg_2367" latency="0" BRAM="-1" DSP="-1" FF="-1" LUT="-1" fileDirectory="C:\Users\raoja\Desktop\uni\520"><\/item>
<item  id="316" filename="imageprosseing/imgpro.c" linenumber="138" name="sext_ln138_2" contextFuncName="blurf" moduleName="blurf" rtlName="sext_ln138_2_fu_1742_p1" latency="0" BRAM="-1" DSP="-1" FF="-1" LUT="-1" fileDirectory="C:\Users\raoja\Desktop\uni\520"><\/item>
<item  id="317" filename="imageprosseing/imgpro.c" linenumber="138" name="select_ln138" contextFuncName="blurf" moduleName="blurf" rtlName="select_ln138_fu_1745_p3" latency="0" BRAM="-1" DSP="-1" FF="0" LUT="32" fileDirectory="C:\Users\raoja\Desktop\uni\520"><\/item>
<item  id="318" filename="imageprosseing/imgpro.c" linenumber="138" name="sub_ln138_1" contextFuncName="blurf" moduleName="blurf" rtlName="sub_ln138_1_fu_1752_p2" latency="0" BRAM="-1" DSP="-1" FF="0" LUT="39" fileDirectory="C:\Users\raoja\Desktop\uni\520"><\/item>
<item  id="319" filename="imageprosseing/imgpro.c" linenumber="138" name="select_ln138_1" contextFuncName="blurf" moduleName="blurf" rtlName="select_ln138_1_fu_1758_p3" latency="0" BRAM="-1" DSP="-1" FF="0" LUT="32" fileDirectory="C:\Users\raoja\Desktop\uni\520"><\/item>
<item  id="329" filename="imageprosseing/imgpro.c" linenumber="126" name="add_ln126" contextFuncName="blurf" moduleName="blurf" rtlName="grp_fu_560_p2" latency="0" BRAM="-1" DSP="-1" FF="0" LUT="32" fileDirectory="C:\Users\raoja\Desktop\uni\520"><\/item>
<item  id="330" filename="imageprosseing/imgpro.c" linenumber="126" name="add_ln126_1" contextFuncName="blurf" moduleName="blurf" rtlName="grp_fu_542_p2" latency="0" BRAM="-1" DSP="-1" FF="0" LUT="39" fileDirectory="C:\Users\raoja\Desktop\uni\520"><\/item>
<item  id="331" filename="imageprosseing/imgpro.c" linenumber="126" name="add_ln126_2" contextFuncName="blurf" moduleName="blurf" rtlName="grp_fu_580_p2" latency="0" BRAM="-1" DSP="-1" FF="0" LUT="32" fileDirectory="C:\Users\raoja\Desktop\uni\520"><\/item>
<item  id="332" filename="imageprosseing/imgpro.c" linenumber="126" name="tmp_22" contextFuncName="blurf" moduleName="blurf" rtlName="tmp_22_reg_2248" latency="0" BRAM="-1" DSP="-1" FF="-1" LUT="-1" fileDirectory="C:\Users\raoja\Desktop\uni\520"><\/item>
<item  id="333" filename="imageprosseing/imgpro.c" linenumber="126" name="sub_ln126" contextFuncName="blurf" moduleName="blurf" rtlName="grp_fu_594_p2" latency="0" BRAM="-1" DSP="-1" FF="0" LUT="39" fileDirectory="C:\Users\raoja\Desktop\uni\520"><\/item>
<item  id="334" filename="imageprosseing/imgpro.c" linenumber="126" name="tmp_7" contextFuncName="blurf" moduleName="blurf" rtlName="reg_634" latency="0" BRAM="-1" DSP="-1" FF="-1" LUT="-1" fileDirectory="C:\Users\raoja\Desktop\uni\520"><\/item>
<item  id="335" filename="imageprosseing/imgpro.c" linenumber="126" name="zext_ln126" contextFuncName="blurf" moduleName="blurf" rtlName="zext_ln126_fu_1410_p1" latency="0" BRAM="-1" DSP="-1" FF="-1" LUT="-1" fileDirectory="C:\Users\raoja\Desktop\uni\520"><\/item>
<item  id="336" filename="imageprosseing/imgpro.c" linenumber="126" name="sub_ln126_1" contextFuncName="blurf" moduleName="blurf" rtlName="sub_ln126_1_fu_1414_p2" latency="0" BRAM="-1" DSP="-1" FF="0" LUT="38" fileDirectory="C:\Users\raoja\Desktop\uni\520"><\/item>
<item  id="337" filename="imageprosseing/imgpro.c" linenumber="126" name="tmp_8" contextFuncName="blurf" moduleName="blurf" rtlName="reg_638" latency="0" BRAM="-1" DSP="-1" FF="-1" LUT="-1" fileDirectory="C:\Users\raoja\Desktop\uni\520"><\/item>
<item  id="338" filename="imageprosseing/imgpro.c" linenumber="126" name="zext_ln126_1" contextFuncName="blurf" moduleName="blurf" rtlName="zext_ln126_1_fu_1420_p1" latency="0" BRAM="-1" DSP="-1" FF="-1" LUT="-1" fileDirectory="C:\Users\raoja\Desktop\uni\520"><\/item>
<item  id="339" filename="imageprosseing/imgpro.c" linenumber="126" name="select_ln126" contextFuncName="blurf" moduleName="blurf" rtlName="select_ln126_fu_1424_p3" latency="0" BRAM="-1" DSP="-1" FF="0" LUT="31" fileDirectory="C:\Users\raoja\Desktop\uni\520"><\/item>
<item  id="340" filename="imageprosseing/imgpro.c" linenumber="126" name="sext_ln126" contextFuncName="blurf" moduleName="blurf" rtlName="sext_ln126_fu_1431_p1" latency="0" BRAM="-1" DSP="-1" FF="-1" LUT="-1" fileDirectory="C:\Users\raoja\Desktop\uni\520"><\/item>
<item  id="350" filename="imageprosseing/imgpro.c" linenumber="113" name="add_ln113" contextFuncName="blurf" moduleName="blurf" rtlName="grp_fu_560_p2" latency="0" BRAM="-1" DSP="-1" FF="0" LUT="32" fileDirectory="C:\Users\raoja\Desktop\uni\520"><\/item>
<item  id="351" filename="imageprosseing/imgpro.c" linenumber="113" name="add_ln113_1" contextFuncName="blurf" moduleName="blurf" rtlName="grp_fu_542_p2" latency="0" BRAM="-1" DSP="-1" FF="0" LUT="39" fileDirectory="C:\Users\raoja\Desktop\uni\520"><\/item>
<item  id="352" filename="imageprosseing/imgpro.c" linenumber="113" name="add_ln113_2" contextFuncName="blurf" moduleName="blurf" rtlName="grp_fu_580_p2" latency="0" BRAM="-1" DSP="-1" FF="0" LUT="32" fileDirectory="C:\Users\raoja\Desktop\uni\520"><\/item>
<item  id="353" filename="imageprosseing/imgpro.c" linenumber="113" name="tmp_21" contextFuncName="blurf" moduleName="blurf" rtlName="tmp_22_reg_2248" latency="0" BRAM="-1" DSP="-1" FF="-1" LUT="-1" fileDirectory="C:\Users\raoja\Desktop\uni\520"><\/item>
<item  id="354" filename="imageprosseing/imgpro.c" linenumber="113" name="sub_ln113" contextFuncName="blurf" moduleName="blurf" rtlName="grp_fu_594_p2" latency="0" BRAM="-1" DSP="-1" FF="0" LUT="39" fileDirectory="C:\Users\raoja\Desktop\uni\520"><\/item>
<item  id="355" filename="imageprosseing/imgpro.c" linenumber="113" name="tmp_5" contextFuncName="blurf" moduleName="blurf" rtlName="reg_634" latency="0" BRAM="-1" DSP="-1" FF="-1" LUT="-1" fileDirectory="C:\Users\raoja\Desktop\uni\520"><\/item>
<item  id="356" filename="imageprosseing/imgpro.c" linenumber="113" name="zext_ln113" contextFuncName="blurf" moduleName="blurf" rtlName="zext_ln113_fu_1436_p1" latency="0" BRAM="-1" DSP="-1" FF="-1" LUT="-1" fileDirectory="C:\Users\raoja\Desktop\uni\520"><\/item>
<item  id="357" filename="imageprosseing/imgpro.c" linenumber="113" name="sub_ln113_1" contextFuncName="blurf" moduleName="blurf" rtlName="sub_ln113_1_fu_1440_p2" latency="0" BRAM="-1" DSP="-1" FF="0" LUT="38" fileDirectory="C:\Users\raoja\Desktop\uni\520"><\/item>
<item  id="358" filename="imageprosseing/imgpro.c" linenumber="113" name="tmp_6" contextFuncName="blurf" moduleName="blurf" rtlName="reg_638" latency="0" BRAM="-1" DSP="-1" FF="-1" LUT="-1" fileDirectory="C:\Users\raoja\Desktop\uni\520"><\/item>
<item  id="359" filename="imageprosseing/imgpro.c" linenumber="113" name="zext_ln113_1" contextFuncName="blurf" moduleName="blurf" rtlName="zext_ln113_1_fu_1446_p1" latency="0" BRAM="-1" DSP="-1" FF="-1" LUT="-1" fileDirectory="C:\Users\raoja\Desktop\uni\520"><\/item>
<item  id="360" filename="imageprosseing/imgpro.c" linenumber="113" name="select_ln113" contextFuncName="blurf" moduleName="blurf" rtlName="select_ln113_fu_1450_p3" latency="0" BRAM="-1" DSP="-1" FF="0" LUT="31" fileDirectory="C:\Users\raoja\Desktop\uni\520"><\/item>
<item  id="361" filename="imageprosseing/imgpro.c" linenumber="113" name="sext_ln113" contextFuncName="blurf" moduleName="blurf" rtlName="sext_ln113_fu_1570_p1" latency="0" BRAM="-1" DSP="-1" FF="-1" LUT="-1" fileDirectory="C:\Users\raoja\Desktop\uni\520"><\/item>
<item  id="371" filename="imageprosseing/imgpro.c" linenumber="101" name="add_ln101" contextFuncName="blurf" moduleName="blurf" rtlName="grp_fu_506_p2" latency="0" BRAM="-1" DSP="-1" FF="0" LUT="32" fileDirectory="C:\Users\raoja\Desktop\uni\520"><\/item>
<item  id="372" filename="imageprosseing/imgpro.c" linenumber="101" name="add_ln101_1" contextFuncName="blurf" moduleName="blurf" rtlName="grp_fu_494_p2" latency="0" BRAM="-1" DSP="-1" FF="0" LUT="39" fileDirectory="C:\Users\raoja\Desktop\uni\520"><\/item>
<item  id="373" filename="imageprosseing/imgpro.c" linenumber="101" name="add_ln101_2" contextFuncName="blurf" moduleName="blurf" rtlName="add_ln101_2_fu_1204_p2" latency="0" BRAM="-1" DSP="-1" FF="0" LUT="32" fileDirectory="C:\Users\raoja\Desktop\uni\520"><\/item>
<item  id="374" filename="imageprosseing/imgpro.c" linenumber="101" name="tmp_20" contextFuncName="blurf" moduleName="blurf" rtlName="tmp_20_reg_2203" latency="0" BRAM="-1" DSP="-1" FF="-1" LUT="-1" fileDirectory="C:\Users\raoja\Desktop\uni\520"><\/item>
<item  id="375" filename="imageprosseing/imgpro.c" linenumber="101" name="sub_ln101" contextFuncName="blurf" moduleName="blurf" rtlName="sub_ln101_fu_1289_p2" latency="0" BRAM="-1" DSP="-1" FF="0" LUT="39" fileDirectory="C:\Users\raoja\Desktop\uni\520"><\/item>
<item  id="376" filename="imageprosseing/imgpro.c" linenumber="101" name="tmp_3" contextFuncName="blurf" moduleName="blurf" rtlName="tmp_3_fu_1294_p4" latency="0" BRAM="-1" DSP="-1" FF="-1" LUT="-1" fileDirectory="C:\Users\raoja\Desktop\uni\520"><\/item>
<item  id="377" filename="imageprosseing/imgpro.c" linenumber="101" name="zext_ln101" contextFuncName="blurf" moduleName="blurf" rtlName="zext_ln101_fu_1304_p1" latency="0" BRAM="-1" DSP="-1" FF="-1" LUT="-1" fileDirectory="C:\Users\raoja\Desktop\uni\520"><\/item>
<item  id="378" filename="imageprosseing/imgpro.c" linenumber="101" name="sub_ln101_1" contextFuncName="blurf" moduleName="blurf" rtlName="sub_ln101_1_fu_1308_p2" latency="0" BRAM="-1" DSP="-1" FF="0" LUT="38" fileDirectory="C:\Users\raoja\Desktop\uni\520"><\/item>
<item  id="379" filename="imageprosseing/imgpro.c" linenumber="101" name="tmp_4" contextFuncName="blurf" moduleName="blurf" rtlName="tmp_4_reg_2208" latency="0" BRAM="-1" DSP="-1" FF="-1" LUT="-1" fileDirectory="C:\Users\raoja\Desktop\uni\520"><\/item>
<item  id="380" filename="imageprosseing/imgpro.c" linenumber="101" name="zext_ln101_1" contextFuncName="blurf" moduleName="blurf" rtlName="zext_ln101_1_fu_1314_p1" latency="0" BRAM="-1" DSP="-1" FF="-1" LUT="-1" fileDirectory="C:\Users\raoja\Desktop\uni\520"><\/item>
<item  id="381" filename="imageprosseing/imgpro.c" linenumber="101" name="select_ln101" contextFuncName="blurf" moduleName="blurf" rtlName="select_ln101_fu_1317_p3" latency="0" BRAM="-1" DSP="-1" FF="0" LUT="31" fileDirectory="C:\Users\raoja\Desktop\uni\520"><\/item>
<item  id="382" filename="imageprosseing/imgpro.c" linenumber="101" name="sext_ln101" contextFuncName="blurf" moduleName="blurf" rtlName="sext_ln101_fu_1574_p1" latency="0" BRAM="-1" DSP="-1" FF="-1" LUT="-1" fileDirectory="C:\Users\raoja\Desktop\uni\520"><\/item>
<item  id="388" filename="imageprosseing/imgpro.c" linenumber="86" name="zext_ln86_1" contextFuncName="blurf" moduleName="blurf" rtlName="zext_ln86_1_fu_976_p1" latency="0" BRAM="-1" DSP="-1" FF="-1" LUT="-1" fileDirectory="C:\Users\raoja\Desktop\uni\520"><\/item>
<item  id="389" filename="imageprosseing/imgpro.c" linenumber="86" name="add_ln86_1" contextFuncName="blurf" moduleName="blurf" rtlName="add_ln86_1_fu_979_p2" latency="0" BRAM="-1" DSP="-1" FF="0" LUT="19" fileDirectory="C:\Users\raoja\Desktop\uni\520"><\/item>
<item  id="390" filename="imageprosseing/imgpro.c" linenumber="86" name="zext_ln86_2" contextFuncName="blurf" moduleName="blurf" rtlName="zext_ln86_2_fu_984_p1" latency="0" BRAM="-1" DSP="-1" FF="-1" LUT="-1" fileDirectory="C:\Users\raoja\Desktop\uni\520"><\/item>
<item  id="392" filename="imageprosseing/imgpro.c" linenumber="89" name="add_ln89_3" contextFuncName="blurf" moduleName="blurf" rtlName="add_ln89_3_fu_1130_p2" latency="0" BRAM="-1" DSP="-1" FF="0" LUT="19" fileDirectory="C:\Users\raoja\Desktop\uni\520"><\/item>
<item  id="393" filename="imageprosseing/imgpro.c" linenumber="89" name="zext_ln89_2" contextFuncName="blurf" moduleName="blurf" rtlName="zext_ln89_2_fu_1134_p1" latency="0" BRAM="-1" DSP="-1" FF="-1" LUT="-1" fileDirectory="C:\Users\raoja\Desktop\uni\520"><\/item>
<item  id="397" filename="imageprosseing/imgpro.c" linenumber="87" name="add_ln87" contextFuncName="blurf" moduleName="blurf" rtlName="grp_fu_484_p2" latency="0" BRAM="-1" DSP="-1" FF="0" LUT="15" fileDirectory="C:\Users\raoja\Desktop\uni\520"><\/item>
<item  id="398" filename="imageprosseing/imgpro.c" linenumber="87" name="zext_ln87" contextFuncName="blurf" moduleName="blurf" rtlName="zext_ln87_fu_989_p1" latency="0" BRAM="-1" DSP="-1" FF="-1" LUT="-1" fileDirectory="C:\Users\raoja\Desktop\uni\520"><\/item>
<item  id="399" filename="imageprosseing/imgpro.c" linenumber="87" name="add_ln87_1" contextFuncName="blurf" moduleName="blurf" rtlName="add_ln87_1_fu_993_p2" latency="0" BRAM="-1" DSP="-1" FF="0" LUT="19" fileDirectory="C:\Users\raoja\Desktop\uni\520"><\/item>
<item  id="400" filename="imageprosseing/imgpro.c" linenumber="87" name="zext_ln87_1" contextFuncName="blurf" moduleName="blurf" rtlName="zext_ln87_1_fu_998_p1" latency="0" BRAM="-1" DSP="-1" FF="-1" LUT="-1" fileDirectory="C:\Users\raoja\Desktop\uni\520"><\/item>
<item  id="402" filename="imageprosseing/imgpro.c" linenumber="88" name="add_ln88" contextFuncName="blurf" moduleName="blurf" rtlName="add_ln88_fu_1139_p2" latency="0" BRAM="-1" DSP="-1" FF="0" LUT="19" fileDirectory="C:\Users\raoja\Desktop\uni\520"><\/item>
<item  id="403" filename="imageprosseing/imgpro.c" linenumber="88" name="zext_ln88_1" contextFuncName="blurf" moduleName="blurf" rtlName="zext_ln88_1_fu_1143_p1" latency="0" BRAM="-1" DSP="-1" FF="-1" LUT="-1" fileDirectory="C:\Users\raoja\Desktop\uni\520"><\/item>
<item  id="408" filename="imageprosseing/imgpro.c" linenumber="89" name="add_ln89" contextFuncName="blurf" moduleName="blurf" rtlName="add_ln89_fu_1228_p2" latency="0" BRAM="-1" DSP="-1" FF="0" LUT="39" fileDirectory="C:\Users\raoja\Desktop\uni\520"><\/item>
<item  id="409" filename="imageprosseing/imgpro.c" linenumber="89" name="add_ln89_1" contextFuncName="blurf" moduleName="blurf" rtlName="add_ln89_1_fu_1324_p2" latency="0" BRAM="-1" DSP="-1" FF="0" LUT="32" fileDirectory="C:\Users\raoja\Desktop\uni\520"><\/item>
<item  id="410" filename="imageprosseing/imgpro.c" linenumber="89" name="add_ln89_2" contextFuncName="blurf" moduleName="blurf" rtlName="add_ln89_2_fu_1330_p2" latency="0" BRAM="-1" DSP="-1" FF="0" LUT="32" fileDirectory="C:\Users\raoja\Desktop\uni\520"><\/item>
<item  id="411" filename="imageprosseing/imgpro.c" linenumber="89" name="tmp_19" contextFuncName="blurf" moduleName="blurf" rtlName="tmp_19_reg_2263" latency="0" BRAM="-1" DSP="-1" FF="-1" LUT="-1" fileDirectory="C:\Users\raoja\Desktop\uni\520"><\/item>
<item  id="412" filename="imageprosseing/imgpro.c" linenumber="89" name="sub_ln89" contextFuncName="blurf" moduleName="blurf" rtlName="sub_ln89_fu_1343_p2" latency="0" BRAM="-1" DSP="-1" FF="0" LUT="39" fileDirectory="C:\Users\raoja\Desktop\uni\520"><\/item>
<item  id="413" filename="imageprosseing/imgpro.c" linenumber="89" name="tmp" contextFuncName="blurf" moduleName="blurf" rtlName="tmp_reg_2268" latency="0" BRAM="-1" DSP="-1" FF="-1" LUT="-1" fileDirectory="C:\Users\raoja\Desktop\uni\520"><\/item>
<item  id="414" filename="imageprosseing/imgpro.c" linenumber="89" name="zext_ln89" contextFuncName="blurf" moduleName="blurf" rtlName="zext_ln89_fu_1457_p1" latency="0" BRAM="-1" DSP="-1" FF="-1" LUT="-1" fileDirectory="C:\Users\raoja\Desktop\uni\520"><\/item>
<item  id="415" filename="imageprosseing/imgpro.c" linenumber="89" name="sub_ln89_1" contextFuncName="blurf" moduleName="blurf" rtlName="sub_ln89_1_fu_1460_p2" latency="0" BRAM="-1" DSP="-1" FF="0" LUT="38" fileDirectory="C:\Users\raoja\Desktop\uni\520"><\/item>
<item  id="416" filename="imageprosseing/imgpro.c" linenumber="89" name="tmp_2" contextFuncName="blurf" moduleName="blurf" rtlName="tmp_2_reg_2273" latency="0" BRAM="-1" DSP="-1" FF="-1" LUT="-1" fileDirectory="C:\Users\raoja\Desktop\uni\520"><\/item>
<item  id="417" filename="imageprosseing/imgpro.c" linenumber="89" name="zext_ln89_1" contextFuncName="blurf" moduleName="blurf" rtlName="zext_ln89_1_fu_1466_p1" latency="0" BRAM="-1" DSP="-1" FF="-1" LUT="-1" fileDirectory="C:\Users\raoja\Desktop\uni\520"><\/item>
<item  id="418" filename="imageprosseing/imgpro.c" linenumber="89" name="select_ln89" contextFuncName="blurf" moduleName="blurf" rtlName="select_ln89_fu_1469_p3" latency="0" BRAM="-1" DSP="-1" FF="0" LUT="31" fileDirectory="C:\Users\raoja\Desktop\uni\520"><\/item>
<item  id="419" filename="imageprosseing/imgpro.c" linenumber="89" name="sext_ln89" contextFuncName="blurf" moduleName="blurf" rtlName="sext_ln89_fu_1476_p1" latency="0" BRAM="-1" DSP="-1" FF="-1" LUT="-1" fileDirectory="C:\Users\raoja\Desktop\uni\520"><\/item>
<item  id="424" filename="imageprosseing/imgpro.c" linenumber="77" name="j" contextFuncName="blurf" moduleName="blurf" rtlName="grp_fu_484_p2" latency="0" BRAM="-1" DSP="-1" FF="0" LUT="15" fileDirectory="C:\Users\raoja\Desktop\uni\520"><\/item>
<\/annotationInfo>
</annotationInfo>
